{
  "AAPL": "/logos/apple.png",
  "MSFT": "/logos/microsoft.png",
  "GOOGL": "/logos/google.png",
  "GOOG": "/logos/google.png",
  "AMZN": "/logos/amazon.png",
  "META": "/logos/meta.png",
  "NVDA": "/logos/nvidia.png",
  "TSLA": "/logos/tesla.png",
  "NFLX": "/logos/netflix.png",
  "ADBE": "/logos/adobe.png",
  "CRM": "/logos/salesforce.png",
  "ORCL": "/logos/oracle.png",
  "IBM": "/logos/ibm.png",
  "INTC": "/logos/intel.png",
  "AMD": "/logos/amd.png",
  "QCOM": "/logos/qualcomm.png",
  "AVGO": "/logos/broadcom.png",
  "JPM": "/logos/jpmorgan.png",
  "GS": "/logos/goldman-sachs.png",
  "MS": "/logos/morgan-stanley.png",
  "BAC": "/logos/bank-of-america.png",
  "V": "/logos/visa.png",
  "MA": "/logos/mastercard.png",
  "DIS": "/logos/disney.png",
  "NKE": "/logos/nike.png",
  "SBUX": "/logos/starbucks.png",
  "MCD": "/logos/mcdonalds.png",
  "KO": "/logos/coca-cola.png",
  "PEP": "/logos/pepsi.png",
  "WMT": "/logos/walmart.png",
  "TGT": "/logos/target.png",
  "HD": "/logos/home-depot.png",
  "COST": "/logos/costco.png",
  "BA": "/logos/boeing.png",
  "XOM": "/logos/exxon-mobil.png",
  "CVX": "/logos/chevron.png",
  "BTC": "/logos/bitcoin.png",
  "ETH": "/logos/ethereum.png",
  "SOL": "/logos/solana.png",
  "XRP": "/logos/xrp.png",
  "DOGE": "/logos/dogecoin.png",
  "GME": "/logos/gamestop.png",
  "COIN": "/logos/coinbase.png",
  "PLTR": "/logos/palantir.png",
  "ARM": "/logos/arm.png"
}